JenniferSig/JenniferSig.py
JenniferSig/__init__.py
JenniferSig-0.0.1.dist-info/METADATA
JenniferSig-0.0.1.dist-info/WHEEL
JenniferSig-0.0.1.dist-info/top_level.txt
JenniferSig-0.0.1.dist-info/RECORD
