Metadata-Version: 2.1
Name: JenniferSig
Version: 0.0.1
Summary: little revison for the assert function
Home-page: UNKNOWN
Author: Dennis Guo
Author-email: dennisguo527@gamil.com
License: MIT
Platform: UNKNOWN
Classifier: Programming Language :: Python :: 3
